fss/__init__.py
fss/constants.py
fss/orchestrator.py
fss/config/__init__.py
fss/config/general.py
fss/config/log.py
fss/config/workers.py
fss/resources/README.rst
fss/resources/requirements.txt
fss/resources/scripts/pathscan
fss/workers/__init__.py
fss/workers/controller_base.py
fss/workers/generator.py
fss/workers/worker_base.py
pathscan-0.2.2.data/scripts/pathscan
pathscan-0.2.2.dist-info/DESCRIPTION.rst
pathscan-0.2.2.dist-info/METADATA
pathscan-0.2.2.dist-info/RECORD
pathscan-0.2.2.dist-info/WHEEL
pathscan-0.2.2.dist-info/metadata.json
pathscan-0.2.2.dist-info/top_level.txt
