Metadata-Version: 2.0
Name: pathscan
Version: 0.2.2
Summary: Search a filesystem using zero or more file and directory filters.
Home-page: https://github.com/dsoprea/PathScan
Author: Dustin Oprea
Author-email: myselfasunder@gmail.com
License: GPL 2
Keywords: filesystem file search scanner
Platform: UNKNOWN
